insyt_secure/__init__.py
insyt_secure/main.py
insyt_secure/project_manager.py
insyt_secure/config/__init__.py
insyt_secure/config/runtime_config.py
insyt_secure/config/settings.py
insyt_secure/executor/__init__.py
insyt_secure/executor/code_executor.py
insyt_secure/utils/__init__.py
insyt_secure/utils/audit_logger.py
insyt_secure/utils/dns_cache.py
insyt_secure/utils/env_manager.py
insyt_secure/utils/logging_config.py
insyt_secure/web/__init__.py
insyt_secure/web/app.py
insyt_secure/web/auth.py
insyt_secure/web/daemon.py
insyt_secure/web/run_server.py
insyt_secure/web/templates/dashboard.html
insyt_secure/web/templates/dashboard_backup_20260105.html
insyt_secure/web/templates/login.html
insyt_secure/web/templates/settings.html
insyt_secure-0.6.32.dist-info/METADATA
insyt_secure-0.6.32.dist-info/WHEEL
insyt_secure-0.6.32.dist-info/entry_points.txt
insyt_secure-0.6.32.dist-info/top_level.txt
insyt_secure-0.6.32.dist-info/RECORD
