Metadata-Version: 2.4
Name: insyt-secure
Version: 0.6.32
Summary: A proprietary service for secure database and API interactions
Author-email: "Insyt.co" <support@insyt.co>
License: Proprietary
Classifier: Programming Language :: Python :: 3
Classifier: Programming Language :: Python :: 3 :: Only
Classifier: Programming Language :: Python :: 3.9
Classifier: Programming Language :: Python :: 3.10
Classifier: Operating System :: OS Independent
Requires-Python: >=3.9
Requires-Dist: paho-mqtt==1.6.1
Requires-Dist: requests==2.31.0
Requires-Dist: python-json-logger==2.0.7
Requires-Dist: httpx==0.25.1
Requires-Dist: tenacity==8.2.3
Requires-Dist: backoff==2.2.1
Requires-Dist: python-dateutil==2.8.2
Requires-Dist: pytz==2023.3
Requires-Dist: protobuf<6.0.0dev,>=3.19.5
Requires-Dist: numpy==2.2.3
Requires-Dist: pandas==2.2.3
Requires-Dist: scipy==1.15.2
Requires-Dist: scikit-learn==1.6.1
Requires-Dist: rapidfuzz==3.5.2
Requires-Dist: statsmodels==0.14.4
Requires-Dist: sympy==1.12
Requires-Dist: polars==0.19.12
Requires-Dist: scikit-survival==0.24.0
Requires-Dist: featuretools==1.27.0
Requires-Dist: numexpr>=2.8.7
Requires-Dist: bottleneck>=1.3.7
Requires-Dist: pyarrow>=14.0.1
Requires-Dist: orjson>=3.9.10
Requires-Dist: thriftpy2>=0.4.16
Requires-Dist: grpcio-tools>=1.59.0
Requires-Dist: flask>=3.0.0
Requires-Dist: werkzeug>=3.0.0
Requires-Dist: bcrypt>=4.0.0
Requires-Dist: waitress>=2.1.0
Requires-Dist: cryptography>=41.0.0
Provides-Extra: rdbms
Requires-Dist: asyncpg>=0.29.0; extra == "rdbms"
Requires-Dist: pg8000==1.29.4; extra == "rdbms"
Requires-Dist: psycopg2-binary==2.9.10; extra == "rdbms"
Requires-Dist: aiomysql>=0.2.0; extra == "rdbms"
Requires-Dist: pymysql==1.1.0; extra == "rdbms"
Requires-Dist: mysql-connector-python>=8.0.31; extra == "rdbms"
Requires-Dist: sqlalchemy==2.0.23; extra == "rdbms"
Requires-Dist: alembic==1.12.1; extra == "rdbms"
Requires-Dist: oracledb>=1.4.1; extra == "rdbms"
Requires-Dist: pymssql>=2.2.7; extra == "rdbms"
Requires-Dist: pyodbc>=4.0.39; extra == "rdbms"
Requires-Dist: clickhouse-driver>=0.2.6; extra == "rdbms"
Requires-Dist: snowflake-connector-python>=3.5.0; extra == "rdbms"
Requires-Dist: duckdb>=0.9.1; extra == "rdbms"
Provides-Extra: postgres
Requires-Dist: asyncpg>=0.29.0; extra == "postgres"
Requires-Dist: pg8000==1.29.4; extra == "postgres"
Requires-Dist: psycopg2-binary==2.9.10; extra == "postgres"
Provides-Extra: mysql
Requires-Dist: aiomysql>=0.2.0; extra == "mysql"
Requires-Dist: pymysql==1.1.0; extra == "mysql"
Requires-Dist: mysql-connector-python>=8.0.31; extra == "mysql"
Provides-Extra: mssql
Requires-Dist: pymssql>=2.2.7; extra == "mssql"
Provides-Extra: oracle
Requires-Dist: oracledb>=1.4.1; extra == "oracle"
Provides-Extra: clickhouse
Requires-Dist: clickhouse-driver>=0.2.6; extra == "clickhouse"
Provides-Extra: snowflake
Requires-Dist: snowflake-connector-python>=3.5.0; extra == "snowflake"
Provides-Extra: duckdb
Requires-Dist: duckdb>=0.9.1; extra == "duckdb"
Provides-Extra: nosql
Requires-Dist: pymongo==4.6.0; extra == "nosql"
Requires-Dist: motor>=3.3.2; extra == "nosql"
Requires-Dist: redis==5.0.1; extra == "nosql"
Requires-Dist: cassandra-driver==3.28.0; extra == "nosql"
Requires-Dist: scylla-driver==3.26.3; extra == "nosql"
Requires-Dist: neo4j==5.14.1; extra == "nosql"
Requires-Dist: elasticsearch==8.11.0; extra == "nosql"
Requires-Dist: couchdb==1.2.0; extra == "nosql"
Requires-Dist: happybase==1.2.0; extra == "nosql"
Requires-Dist: pysolr==3.9.0; extra == "nosql"
Provides-Extra: mongodb
Requires-Dist: pymongo==4.6.0; extra == "mongodb"
Requires-Dist: motor>=3.3.2; extra == "mongodb"
Provides-Extra: redis
Requires-Dist: redis==5.0.1; extra == "redis"
Provides-Extra: cassandra
Requires-Dist: cassandra-driver==3.28.0; extra == "cassandra"
Provides-Extra: neo4j
Requires-Dist: neo4j==5.14.1; extra == "neo4j"
Provides-Extra: elasticsearch
Requires-Dist: elasticsearch==8.11.0; extra == "elasticsearch"
Provides-Extra: couchdb
Requires-Dist: couchdb==1.2.0; extra == "couchdb"
Provides-Extra: happybase
Requires-Dist: happybase==1.2.0; extra == "happybase"
Provides-Extra: pysolr
Requires-Dist: pysolr==3.9.0; extra == "pysolr"
Provides-Extra: vector
Requires-Dist: pinecone-client==2.2.4; extra == "vector"
Requires-Dist: qdrant-client==1.13.3; extra == "vector"
Requires-Dist: milvus==2.2.16; extra == "vector"
Requires-Dist: weaviate-client==3.24.1; extra == "vector"
Requires-Dist: pyvespa==0.36.0; extra == "vector"
Requires-Dist: chromadb>=0.4.17; extra == "vector"
Requires-Dist: faiss-cpu>=1.7.4; extra == "vector"
Provides-Extra: pinecone
Requires-Dist: pinecone-client==2.2.4; extra == "pinecone"
Provides-Extra: qdrant
Requires-Dist: qdrant-client==1.13.3; extra == "qdrant"
Provides-Extra: milvus
Requires-Dist: milvus==2.2.16; extra == "milvus"
Provides-Extra: weaviate
Requires-Dist: weaviate-client==3.24.1; extra == "weaviate"
Provides-Extra: pyvespa
Requires-Dist: pyvespa==0.36.0; extra == "pyvespa"
Provides-Extra: chroma
Requires-Dist: chromadb>=0.4.17; extra == "chroma"
Provides-Extra: faiss
Requires-Dist: faiss-cpu>=1.7.4; extra == "faiss"
Provides-Extra: cloud
Requires-Dist: boto3==1.33.6; extra == "cloud"
Requires-Dist: google-cloud-storage==2.13.0; extra == "cloud"
Requires-Dist: google-cloud-bigquery==3.11.4; extra == "cloud"
Requires-Dist: google-cloud-firestore==2.13.1; extra == "cloud"
Requires-Dist: azure-cosmos==4.5.1; extra == "cloud"
Requires-Dist: azure-storage-blob==12.19.0; extra == "cloud"
Requires-Dist: azure-data-tables==12.4.4; extra == "cloud"
Provides-Extra: aws
Requires-Dist: boto3==1.33.6; extra == "aws"
Requires-Dist: google-cloud-storage==2.13.0; extra == "aws"
Requires-Dist: google-cloud-bigquery==3.11.4; extra == "aws"
Requires-Dist: google-cloud-firestore==2.13.1; extra == "aws"
Provides-Extra: azure
Requires-Dist: azure-cosmos==4.5.1; extra == "azure"
Requires-Dist: azure-storage-blob==12.19.0; extra == "azure"
Requires-Dist: azure-data-tables==12.4.4; extra == "azure"
Provides-Extra: messaging
Requires-Dist: confluent-kafka>=2.3.0; extra == "messaging"
Requires-Dist: pulsar-client>=3.6.1; extra == "messaging"
Requires-Dist: pika==1.3.1; extra == "messaging"
Requires-Dist: nats-py==2.6.0; extra == "messaging"
Requires-Dist: stomp.py==8.1.0; extra == "messaging"
Requires-Dist: google-cloud-pubsub==2.18.4; extra == "messaging"
Provides-Extra: kafka
Requires-Dist: confluent-kafka>=2.3.0; extra == "kafka"
Provides-Extra: pulsar
Requires-Dist: pulsar-client>=3.6.1; extra == "pulsar"
Provides-Extra: rabbitmq
Requires-Dist: pika==1.3.1; extra == "rabbitmq"
Provides-Extra: all
Requires-Dist: insyt-secure[cloud,messaging,nosql,rdbms,vector]; extra == "all"
Provides-Extra: all-performance
Requires-Dist: insyt-secure[all,performance]; extra == "all-performance"
